cullinan/__init__.py
cullinan/app.py
cullinan/application.py
cullinan/bootstrap.py
cullinan/config.py
cullinan/deprecation.py
cullinan/exceptions.py
cullinan/extensions.py
cullinan/lifecycle_hooks.py
cullinan/logging_utils.py
cullinan/module_scanner.py
cullinan/path_utils.py
cullinan/scan_stats.py
cullinan/scanner.py
cullinan/websocket_registry.py
cullinan/codec/__init__.py
cullinan/codec/base.py
cullinan/codec/errors.py
cullinan/codec/form_codec.py
cullinan/codec/json_codec.py
cullinan/codec/registry.py
cullinan/controller/__init__.py
cullinan/controller/core.py
cullinan/controller/registry.py
cullinan/controller/stateless_validator.py
cullinan/core/__init__.py
cullinan/core/application_context.py
cullinan/core/conditions.py
cullinan/core/context.py
cullinan/core/decorators.py
cullinan/core/definitions.py
cullinan/core/diagnostics.py
cullinan/core/exceptions.py
cullinan/core/extensions.py
cullinan/core/facade.py
cullinan/core/factory.py
cullinan/core/lifecycle.py
cullinan/core/lifecycle_enhanced.py
cullinan/core/pending.py
cullinan/core/provider_source.py
cullinan/core/registry.py
cullinan/core/scope_manager.py
cullinan/core/types.py
cullinan/core/container/__init__.py
cullinan/core/container/context.py
cullinan/core/container/definitions.py
cullinan/core/container/factory.py
cullinan/core/container/scope.py
cullinan/core/diagnostics/__init__.py
cullinan/core/diagnostics/exceptions.py
cullinan/core/diagnostics/renderer.py
cullinan/core/diagnostics/types.py
cullinan/core/lifecycle/__init__.py
cullinan/core/lifecycle/enhanced.py
cullinan/core/lifecycle/events.py
cullinan/core/lifecycle/manager.py
cullinan/core/request/__init__.py
cullinan/core/request/context.py
cullinan/handler/__init__.py
cullinan/handler/base.py
cullinan/handler/registry.py
cullinan/middleware/__init__.py
cullinan/middleware/base.py
cullinan/middleware/body_decoder.py
cullinan/middleware/legacy.py
cullinan/middleware/registry.py
cullinan/monitoring/__init__.py
cullinan/monitoring/hooks.py
cullinan-0.91.dist-info/licenses/LICENSE
cullinan-0.91.dist-info/METADATA
cullinan-0.91.dist-info/WHEEL
cullinan-0.91.dist-info/top_level.txt
cullinan-0.91.dist-info/RECORD
