Metadata-Version: 2.4
Name: cullinan
Version: 0.91
Summary: Cullinan is written based on tornado and Sqlalchemy to help the project quickly build web application
Home-page: https://github.com/plumeink/Cullinan
Author: plumeink
Author-email: official@plumeink.com
License: MIT
Project-URL: Source, https://github.com/plumeink/Cullinan
Project-URL: Wiki, https://github.com/plumeink/Cullinan/wiki
Classifier: Programming Language :: Python :: 3.7
Classifier: Programming Language :: Python :: 3.8
Classifier: Programming Language :: Python :: 3.9
Classifier: Programming Language :: Python :: 3.10
Classifier: Programming Language :: Python :: 3.11
Classifier: Programming Language :: Python :: 3.12
Classifier: Programming Language :: Python :: 3.13
Classifier: License :: OSI Approved :: MIT License
Classifier: Operating System :: OS Independent
Requires-Python: >=3.7
License-File: LICENSE
Requires-Dist: tornado
Requires-Dist: python-dotenv
Requires-Dist: contextvars
Dynamic: author
Dynamic: author-email
Dynamic: classifier
Dynamic: description
Dynamic: description-content-type
Dynamic: home-page
Dynamic: license
Dynamic: license-file
Dynamic: project-url
Dynamic: requires-dist
Dynamic: requires-python
Dynamic: summary
